{
  "total_count": 103,
  "incomplete_results": false,
  "items": [
    {
      "login": "tiket",
      "id": 885658,
      "node_id": "MDEyOk9yZ2FuaXphdGlvbjg4NTY1OA==",
      "avatar_url": "https://avatars3.githubusercontent.com/u/885658?v=4",
      "gravatar_id": "",
      "url": "https://api.github.com/users/tiket",
      "html_url": "https://github.com/tiket",
      "followers_url": "https://api.github.com/users/tiket/followers",
      "following_url": "https://api.github.com/users/tiket/following{/other_user}",
      "gists_url": "https://api.github.com/users/tiket/gists{/gist_id}",
      "starred_url": "https://api.github.com/users/tiket/starred{/owner}{/repo}",
      "subscriptions_url": "https://api.github.com/users/tiket/subscriptions",
      "organizations_url": "https://api.github.com/users/tiket/orgs",
      "repos_url": "https://api.github.com/users/tiket/repos",
      "events_url": "https://api.github.com/users/tiket/events{/privacy}",
      "received_events_url": "https://api.github.com/users/tiket/received_events",
      "type": "Organization",
      "site_admin": false,
      "score": 1.0
    },
    {
      "login": "Tiketti",
      "id": 6553662,
      "node_id": "MDQ6VXNlcjY1NTM2NjI=",
      "avatar_url": "https://avatars3.githubusercontent.com/u/6553662?v=4",
      "gravatar_id": "",
      "url": "https://api.github.com/users/Tiketti",
      "html_url": "https://github.com/Tiketti",
      "followers_url": "https://api.github.com/users/Tiketti/followers",
      "following_url": "https://api.github.com/users/Tiketti/following{/other_user}",
      "gists_url": "https://api.github.com/users/Tiketti/gists{/gist_id}",
      "starred_url": "https://api.github.com/users/Tiketti/starred{/owner}{/repo}",
      "subscriptions_url": "https://api.github.com/users/Tiketti/subscriptions",
      "organizations_url": "https://api.github.com/users/Tiketti/orgs",
      "repos_url": "https://api.github.com/users/Tiketti/repos",
      "events_url": "https://api.github.com/users/Tiketti/events{/privacy}",
      "received_events_url": "https://api.github.com/users/Tiketti/received_events",
      "type": "User",
      "site_admin": false,
      "score": 1.0
    },
    {
      "login": "ugglr",
      "id": 5120880,
      "node_id": "MDQ6VXNlcjUxMjA4ODA=",
      "avatar_url": "https://avatars3.githubusercontent.com/u/5120880?v=4",
      "gravatar_id": "",
      "url": "https://api.github.com/users/ugglr",
      "html_url": "https://github.com/ugglr",
      "followers_url": "https://api.github.com/users/ugglr/followers",
      "following_url": "https://api.github.com/users/ugglr/following{/other_user}",
      "gists_url": "https://api.github.com/users/ugglr/gists{/gist_id}",
      "starred_url": "https://api.github.com/users/ugglr/starred{/owner}{/repo}",
      "subscriptions_url": "https://api.github.com/users/ugglr/subscriptions",
      "organizations_url": "https://api.github.com/users/ugglr/orgs",
      "repos_url": "https://api.github.com/users/ugglr/repos",
      "events_url": "https://api.github.com/users/ugglr/events{/privacy}",
      "received_events_url": "https://api.github.com/users/ugglr/received_events",
      "type": "User",
      "site_admin": false,
      "score": 1.0
    },
    {
      "login": "dsapoetra",
      "id": 3592714,
      "node_id": "MDQ6VXNlcjM1OTI3MTQ=",
      "avatar_url": "https://avatars3.githubusercontent.com/u/3592714?v=4",
      "gravatar_id": "",
      "url": "https://api.github.com/users/dsapoetra",
      "html_url": "https://github.com/dsapoetra",
      "followers_url": "https://api.github.com/users/dsapoetra/followers",
      "following_url": "https://api.github.com/users/dsapoetra/following{/other_user}",
      "gists_url": "https://api.github.com/users/dsapoetra/gists{/gist_id}",
      "starred_url": "https://api.github.com/users/dsapoetra/starred{/owner}{/repo}",
      "subscriptions_url": "https://api.github.com/users/dsapoetra/subscriptions",
      "organizations_url": "https://api.github.com/users/dsapoetra/orgs",
      "repos_url": "https://api.github.com/users/dsapoetra/repos",
      "events_url": "https://api.github.com/users/dsapoetra/events{/privacy}",
      "received_events_url": "https://api.github.com/users/dsapoetra/received_events",
      "type": "User",
      "site_admin": false,
      "score": 1.0
    },
    {
      "login": "fungilation",
      "id": 3803466,
      "node_id": "MDQ6VXNlcjM4MDM0NjY=",
      "avatar_url": "https://avatars3.githubusercontent.com/u/3803466?v=4",
      "gravatar_id": "",
      "url": "https://api.github.com/users/fungilation",
      "html_url": "https://github.com/fungilation",
      "followers_url": "https://api.github.com/users/fungilation/followers",
      "following_url": "https://api.github.com/users/fungilation/following{/other_user}",
      "gists_url": "https://api.github.com/users/fungilation/gists{/gist_id}",
      "starred_url": "https://api.github.com/users/fungilation/starred{/owner}{/repo}",
      "subscriptions_url": "https://api.github.com/users/fungilation/subscriptions",
      "organizations_url": "https://api.github.com/users/fungilation/orgs",
      "repos_url": "https://api.github.com/users/fungilation/repos",
      "events_url": "https://api.github.com/users/fungilation/events{/privacy}",
      "received_events_url": "https://api.github.com/users/fungilation/received_events",
      "type": "User",
      "site_admin": false,
      "score": 1.0
    },
    {
      "login": "Tiketoke",
      "id": 28427268,
      "node_id": "MDQ6VXNlcjI4NDI3MjY4",
      "avatar_url": "https://avatars2.githubusercontent.com/u/28427268?v=4",
      "gravatar_id": "",
      "url": "https://api.github.com/users/Tiketoke",
      "html_url": "https://github.com/Tiketoke",
      "followers_url": "https://api.github.com/users/Tiketoke/followers",
      "following_url": "https://api.github.com/users/Tiketoke/following{/other_user}",
      "gists_url": "https://api.github.com/users/Tiketoke/gists{/gist_id}",
      "starred_url": "https://api.github.com/users/Tiketoke/starred{/owner}{/repo}",
      "subscriptions_url": "https://api.github.com/users/Tiketoke/subscriptions",
      "organizations_url": "https://api.github.com/users/Tiketoke/orgs",
      "repos_url": "https://api.github.com/users/Tiketoke/repos",
      "events_url": "https://api.github.com/users/Tiketoke/events{/privacy}",
      "received_events_url": "https://api.github.com/users/Tiketoke/received_events",
      "type": "User",
      "site_admin": false,
      "score": 1.0
    },
    {
      "login": "tiket-oss",
      "id": 45250522,
      "node_id": "MDEyOk9yZ2FuaXphdGlvbjQ1MjUwNTIy",
      "avatar_url": "https://avatars3.githubusercontent.com/u/45250522?v=4",
      "gravatar_id": "",
      "url": "https://api.github.com/users/tiket-oss",
      "html_url": "https://github.com/tiket-oss",
      "followers_url": "https://api.github.com/users/tiket-oss/followers",
      "following_url": "https://api.github.com/users/tiket-oss/following{/other_user}",
      "gists_url": "https://api.github.com/users/tiket-oss/gists{/gist_id}",
      "starred_url": "https://api.github.com/users/tiket-oss/starred{/owner}{/repo}",
      "subscriptions_url": "https://api.github.com/users/tiket-oss/subscriptions",
      "organizations_url": "https://api.github.com/users/tiket-oss/orgs",
      "repos_url": "https://api.github.com/users/tiket-oss/repos",
      "events_url": "https://api.github.com/users/tiket-oss/events{/privacy}",
      "received_events_url": "https://api.github.com/users/tiket-oss/received_events",
      "type": "Organization",
      "site_admin": false,
      "score": 1.0
    },
    {
      "login": "vdanny",
      "id": 13584885,
      "node_id": "MDQ6VXNlcjEzNTg0ODg1",
      "avatar_url": "https://avatars2.githubusercontent.com/u/13584885?v=4",
      "gravatar_id": "",
      "url": "https://api.github.com/users/vdanny",
      "html_url": "https://github.com/vdanny",
      "followers_url": "https://api.github.com/users/vdanny/followers",
      "following_url": "https://api.github.com/users/vdanny/following{/other_user}",
      "gists_url": "https://api.github.com/users/vdanny/gists{/gist_id}",
      "starred_url": "https://api.github.com/users/vdanny/starred{/owner}{/repo}",
      "subscriptions_url": "https://api.github.com/users/vdanny/subscriptions",
      "organizations_url": "https://api.github.com/users/vdanny/orgs",
      "repos_url": "https://api.github.com/users/vdanny/repos",
      "events_url": "https://api.github.com/users/vdanny/events{/privacy}",
      "received_events_url": "https://api.github.com/users/vdanny/received_events",
      "type": "User",
      "site_admin": false,
      "score": 1.0
    },
    {
      "login": "tiketiskte",
      "id": 49359899,
      "node_id": "MDQ6VXNlcjQ5MzU5ODk5",
      "avatar_url": "https://avatars3.githubusercontent.com/u/49359899?v=4",
      "gravatar_id": "",
      "url": "https://api.github.com/users/tiketiskte",
      "html_url": "https://github.com/tiketiskte",
      "followers_url": "https://api.github.com/users/tiketiskte/followers",
      "following_url": "https://api.github.com/users/tiketiskte/following{/other_user}",
      "gists_url": "https://api.github.com/users/tiketiskte/gists{/gist_id}",
      "starred_url": "https://api.github.com/users/tiketiskte/starred{/owner}{/repo}",
      "subscriptions_url": "https://api.github.com/users/tiketiskte/subscriptions",
      "organizations_url": "https://api.github.com/users/tiketiskte/orgs",
      "repos_url": "https://api.github.com/users/tiketiskte/repos",
      "events_url": "https://api.github.com/users/tiketiskte/events{/privacy}",
      "received_events_url": "https://api.github.com/users/tiketiskte/received_events",
      "type": "User",
      "site_admin": false,
      "score": 1.0
    },
    {
      "login": "vanrahman31",
      "id": 44625840,
      "node_id": "MDQ6VXNlcjQ0NjI1ODQw",
      "avatar_url": "https://avatars1.githubusercontent.com/u/44625840?v=4",
      "gravatar_id": "",
      "url": "https://api.github.com/users/vanrahman31",
      "html_url": "https://github.com/vanrahman31",
      "followers_url": "https://api.github.com/users/vanrahman31/followers",
      "following_url": "https://api.github.com/users/vanrahman31/following{/other_user}",
      "gists_url": "https://api.github.com/users/vanrahman31/gists{/gist_id}",
      "starred_url": "https://api.github.com/users/vanrahman31/starred{/owner}{/repo}",
      "subscriptions_url": "https://api.github.com/users/vanrahman31/subscriptions",
      "organizations_url": "https://api.github.com/users/vanrahman31/orgs",
      "repos_url": "https://api.github.com/users/vanrahman31/repos",
      "events_url": "https://api.github.com/users/vanrahman31/events{/privacy}",
      "received_events_url": "https://api.github.com/users/vanrahman31/received_events",
      "type": "User",
      "site_admin": false,
      "score": 1.0
    },
    {
      "login": "tiketagency",
      "id": 16734784,
      "node_id": "MDEyOk9yZ2FuaXphdGlvbjE2NzM0Nzg0",
      "avatar_url": "https://avatars1.githubusercontent.com/u/16734784?v=4",
      "gravatar_id": "",
      "url": "https://api.github.com/users/tiketagency",
      "html_url": "https://github.com/tiketagency",
      "followers_url": "https://api.github.com/users/tiketagency/followers",
      "following_url": "https://api.github.com/users/tiketagency/following{/other_user}",
      "gists_url": "https://api.github.com/users/tiketagency/gists{/gist_id}",
      "starred_url": "https://api.github.com/users/tiketagency/starred{/owner}{/repo}",
      "subscriptions_url": "https://api.github.com/users/tiketagency/subscriptions",
      "organizations_url": "https://api.github.com/users/tiketagency/orgs",
      "repos_url": "https://api.github.com/users/tiketagency/repos",
      "events_url": "https://api.github.com/users/tiketagency/events{/privacy}",
      "received_events_url": "https://api.github.com/users/tiketagency/received_events",
      "type": "Organization",
      "site_admin": false,
      "score": 1.0
    },
    {
      "login": "tiket-in",
      "id": 58902901,
      "node_id": "MDEyOk9yZ2FuaXphdGlvbjU4OTAyOTAx",
      "avatar_url": "https://avatars1.githubusercontent.com/u/58902901?v=4",
      "gravatar_id": "",
      "url": "https://api.github.com/users/tiket-in",
      "html_url": "https://github.com/tiket-in",
      "followers_url": "https://api.github.com/users/tiket-in/followers",
      "following_url": "https://api.github.com/users/tiket-in/following{/other_user}",
      "gists_url": "https://api.github.com/users/tiket-in/gists{/gist_id}",
      "starred_url": "https://api.github.com/users/tiket-in/starred{/owner}{/repo}",
      "subscriptions_url": "https://api.github.com/users/tiket-in/subscriptions",
      "organizations_url": "https://api.github.com/users/tiket-in/orgs",
      "repos_url": "https://api.github.com/users/tiket-in/repos",
      "events_url": "https://api.github.com/users/tiket-in/events{/privacy}",
      "received_events_url": "https://api.github.com/users/tiket-in/received_events",
      "type": "Organization",
      "site_admin": false,
      "score": 1.0
    },
    {
      "login": "tiketdataagung",
      "id": 43364449,
      "node_id": "MDQ6VXNlcjQzMzY0NDQ5",
      "avatar_url": "https://avatars1.githubusercontent.com/u/43364449?v=4",
      "gravatar_id": "",
      "url": "https://api.github.com/users/tiketdataagung",
      "html_url": "https://github.com/tiketdataagung",
      "followers_url": "https://api.github.com/users/tiketdataagung/followers",
      "following_url": "https://api.github.com/users/tiketdataagung/following{/other_user}",
      "gists_url": "https://api.github.com/users/tiketdataagung/gists{/gist_id}",
      "starred_url": "https://api.github.com/users/tiketdataagung/starred{/owner}{/repo}",
      "subscriptions_url": "https://api.github.com/users/tiketdataagung/subscriptions",
      "organizations_url": "https://api.github.com/users/tiketdataagung/orgs",
      "repos_url": "https://api.github.com/users/tiketdataagung/repos",
      "events_url": "https://api.github.com/users/tiketdataagung/events{/privacy}",
      "received_events_url": "https://api.github.com/users/tiketdataagung/received_events",
      "type": "User",
      "site_admin": false,
      "score": 1.0
    },
    {
      "login": "tiketdatamaria",
      "id": 42638074,
      "node_id": "MDQ6VXNlcjQyNjM4MDc0",
      "avatar_url": "https://avatars1.githubusercontent.com/u/42638074?v=4",
      "gravatar_id": "",
      "url": "https://api.github.com/users/tiketdatamaria",
      "html_url": "https://github.com/tiketdatamaria",
      "followers_url": "https://api.github.com/users/tiketdatamaria/followers",
      "following_url": "https://api.github.com/users/tiketdatamaria/following{/other_user}",
      "gists_url": "https://api.github.com/users/tiketdatamaria/gists{/gist_id}",
      "starred_url": "https://api.github.com/users/tiketdatamaria/starred{/owner}{/repo}",
      "subscriptions_url": "https://api.github.com/users/tiketdatamaria/subscriptions",
      "organizations_url": "https://api.github.com/users/tiketdatamaria/orgs",
      "repos_url": "https://api.github.com/users/tiketdatamaria/repos",
      "events_url": "https://api.github.com/users/tiketdatamaria/events{/privacy}",
      "received_events_url": "https://api.github.com/users/tiketdatamaria/received_events",
      "type": "User",
      "site_admin": false,
      "score": 1.0
    },
    {
      "login": "namaiwa",
      "id": 31990380,
      "node_id": "MDQ6VXNlcjMxOTkwMzgw",
      "avatar_url": "https://avatars1.githubusercontent.com/u/31990380?v=4",
      "gravatar_id": "",
      "url": "https://api.github.com/users/namaiwa",
      "html_url": "https://github.com/namaiwa",
      "followers_url": "https://api.github.com/users/namaiwa/followers",
      "following_url": "https://api.github.com/users/namaiwa/following{/other_user}",
      "gists_url": "https://api.github.com/users/namaiwa/gists{/gist_id}",
      "starred_url": "https://api.github.com/users/namaiwa/starred{/owner}{/repo}",
      "subscriptions_url": "https://api.github.com/users/namaiwa/subscriptions",
      "organizations_url": "https://api.github.com/users/namaiwa/orgs",
      "repos_url": "https://api.github.com/users/namaiwa/repos",
      "events_url": "https://api.github.com/users/namaiwa/events{/privacy}",
      "received_events_url": "https://api.github.com/users/namaiwa/received_events",
      "type": "User",
      "site_admin": false,
      "score": 1.0
    },
    {
      "login": "tiketo",
      "id": 25151609,
      "node_id": "MDQ6VXNlcjI1MTUxNjA5",
      "avatar_url": "https://avatars1.githubusercontent.com/u/25151609?v=4",
      "gravatar_id": "",
      "url": "https://api.github.com/users/tiketo",
      "html_url": "https://github.com/tiketo",
      "followers_url": "https://api.github.com/users/tiketo/followers",
      "following_url": "https://api.github.com/users/tiketo/following{/other_user}",
      "gists_url": "https://api.github.com/users/tiketo/gists{/gist_id}",
      "starred_url": "https://api.github.com/users/tiketo/starred{/owner}{/repo}",
      "subscriptions_url": "https://api.github.com/users/tiketo/subscriptions",
      "organizations_url": "https://api.github.com/users/tiketo/orgs",
      "repos_url": "https://api.github.com/users/tiketo/repos",
      "events_url": "https://api.github.com/users/tiketo/events{/privacy}",
      "received_events_url": "https://api.github.com/users/tiketo/received_events",
      "type": "User",
      "site_admin": false,
      "score": 1.0
    },
    {
      "login": "Tiketal",
      "id": 29183666,
      "node_id": "MDQ6VXNlcjI5MTgzNjY2",
      "avatar_url": "https://avatars0.githubusercontent.com/u/29183666?v=4",
      "gravatar_id": "",
      "url": "https://api.github.com/users/Tiketal",
      "html_url": "https://github.com/Tiketal",
      "followers_url": "https://api.github.com/users/Tiketal/followers",
      "following_url": "https://api.github.com/users/Tiketal/following{/other_user}",
      "gists_url": "https://api.github.com/users/Tiketal/gists{/gist_id}",
      "starred_url": "https://api.github.com/users/Tiketal/starred{/owner}{/repo}",
      "subscriptions_url": "https://api.github.com/users/Tiketal/subscriptions",
      "organizations_url": "https://api.github.com/users/Tiketal/orgs",
      "repos_url": "https://api.github.com/users/Tiketal/repos",
      "events_url": "https://api.github.com/users/Tiketal/events{/privacy}",
      "received_events_url": "https://api.github.com/users/Tiketal/received_events",
      "type": "User",
      "site_admin": false,
      "score": 1.0
    },
    {
      "login": "tiketdata-Hizkia",
      "id": 47315007,
      "node_id": "MDQ6VXNlcjQ3MzE1MDA3",
      "avatar_url": "https://avatars0.githubusercontent.com/u/47315007?v=4",
      "gravatar_id": "",
      "url": "https://api.github.com/users/tiketdata-Hizkia",
      "html_url": "https://github.com/tiketdata-Hizkia",
      "followers_url": "https://api.github.com/users/tiketdata-Hizkia/followers",
      "following_url": "https://api.github.com/users/tiketdata-Hizkia/following{/other_user}",
      "gists_url": "https://api.github.com/users/tiketdata-Hizkia/gists{/gist_id}",
      "starred_url": "https://api.github.com/users/tiketdata-Hizkia/starred{/owner}{/repo}",
      "subscriptions_url": "https://api.github.com/users/tiketdata-Hizkia/subscriptions",
      "organizations_url": "https://api.github.com/users/tiketdata-Hizkia/orgs",
      "repos_url": "https://api.github.com/users/tiketdata-Hizkia/repos",
      "events_url": "https://api.github.com/users/tiketdata-Hizkia/events{/privacy}",
      "received_events_url": "https://api.github.com/users/tiketdata-Hizkia/received_events",
      "type": "User",
      "site_admin": false,
      "score": 1.0
    },
    {
      "login": "tiketdatailyas",
      "id": 52735204,
      "node_id": "MDQ6VXNlcjUyNzM1MjA0",
      "avatar_url": "https://avatars0.githubusercontent.com/u/52735204?v=4",
      "gravatar_id": "",
      "url": "https://api.github.com/users/tiketdatailyas",
      "html_url": "https://github.com/tiketdatailyas",
      "followers_url": "https://api.github.com/users/tiketdatailyas/followers",
      "following_url": "https://api.github.com/users/tiketdatailyas/following{/other_user}",
      "gists_url": "https://api.github.com/users/tiketdatailyas/gists{/gist_id}",
      "starred_url": "https://api.github.com/users/tiketdatailyas/starred{/owner}{/repo}",
      "subscriptions_url": "https://api.github.com/users/tiketdatailyas/subscriptions",
      "organizations_url": "https://api.github.com/users/tiketdatailyas/orgs",
      "repos_url": "https://api.github.com/users/tiketdatailyas/repos",
      "events_url": "https://api.github.com/users/tiketdatailyas/events{/privacy}",
      "received_events_url": "https://api.github.com/users/tiketdatailyas/received_events",
      "type": "User",
      "site_admin": false,
      "score": 1.0
    },
    {
      "login": "tiketmaria",
      "id": 41613999,
      "node_id": "MDQ6VXNlcjQxNjEzOTk5",
      "avatar_url": "https://avatars2.githubusercontent.com/u/41613999?v=4",
      "gravatar_id": "",
      "url": "https://api.github.com/users/tiketmaria",
      "html_url": "https://github.com/tiketmaria",
      "followers_url": "https://api.github.com/users/tiketmaria/followers",
      "following_url": "https://api.github.com/users/tiketmaria/following{/other_user}",
      "gists_url": "https://api.github.com/users/tiketmaria/gists{/gist_id}",
      "starred_url": "https://api.github.com/users/tiketmaria/starred{/owner}{/repo}",
      "subscriptions_url": "https://api.github.com/users/tiketmaria/subscriptions",
      "organizations_url": "https://api.github.com/users/tiketmaria/orgs",
      "repos_url": "https://api.github.com/users/tiketmaria/repos",
      "events_url": "https://api.github.com/users/tiketmaria/events{/privacy}",
      "received_events_url": "https://api.github.com/users/tiketmaria/received_events",
      "type": "User",
      "site_admin": false,
      "score": 1.0
    }
  ]
}